<xml>
   <Table System="accounting" SoftDelete="1" CanModify="0" CanDelete="0" name="Due dated">
      <Field Caption="Cash receipt" File="accounting.cashreceipt" Size="4" Type="2" Force="1" name="cashreceipt"/>
      <Field Caption="Due date" Size="4" Type="5" Force="1" name="duedate"/>
      <Field Caption="Cheque No." Size="12" name="cheque"/>
      <Field Caption="Bank" File="accounting.bank" Size="2" Type="2" name="bank"/>
      <Field Caption="Amount" Total="1" Format="######.##" Size="4" Type="4" Force="1" name="amount"/>
      <Field Caption="Journal" Total="1" File="accounting.journal" Size="4" Type="2" name="journal"/>
      <Field Caption="Modified" Hide="1" System="1" Size="8" Type="5" name="@modify_stamp"/>
      <Field Caption="SoftDelete" Format="b" Hide="1" System="1" Size="1" Type="2" name="@delete" HideReport="1"/>
      <Index name="cashduedate">
         <IndexEntry name="cashreceipt"/>
         <IndexEntry name="duedate"/>
         <IndexEntry name="cheque"/>
      </Index>
      <Index name="cashduedate[bank]">
         <IndexEntry name="bank"/>
         <IndexEntry name="cashreceipt"/>
         <IndexEntry name="duedate"/>
         <IndexEntry name="cheque"/>
      </Index>
      <Index name="cashduedate[journal]">
         <IndexEntry name="journal"/>
         <IndexEntry name="cashreceipt"/>
         <IndexEntry name="duedate"/>
         <IndexEntry name="cheque"/>
      </Index>
      <Index name="cashduedate_duedate">
         <IndexEntry name="duedate"/>
         <IndexEntry name="cashreceipt"/>
         <IndexEntry name="cheque"/>
      </Index>
   </Table>
</xml>
